test/__init__.py
test/test_advice.py
test/test_alert.py
test/test_alert_info.py
test/test_alert_info_area.py
test/test_alert_info_area_geocode.py
test/test_alert_info_event_code.py
test/test_alert_info_parameter.py
test/test_alert_info_resource.py
test/test_archive_api.py
test/test_avalanche_problem.py
test/test_avalanche_warning_by_coordinates_api.py
test/test_avalanche_warning_by_region_api.py
test/test_avalanche_warning_detail.py
test/test_avalanche_warning_simple.py
test/test_cap_api.py
test/test_code_page_data_item.py
test/test_county.py
test/test_decoder_fallback.py
test/test_encoder_fallback.py
test/test_encoding.py
test/test_formatted_content_result_alert.py
test/test_formatted_content_result_list_alert.py
test/test_i_required_member_selector.py
test/test_measurement_sub_type.py
test/test_measurement_type.py
test/test_media_type_formatter.py
test/test_media_type_header_value.py
test/test_media_type_mapping.py
test/test_mountain_weather.py
test/test_municipality.py
test/test_name_value_header_value.py
test/test_obs_warning.py
test/test_region.py
test/test_region_api.py
test/test_region_summary.py
test/test_region_summary_api.py
test/test_region_summary_obs.py
test/test_summary.py
test/test_warning_api.py
varsom_avalanche_client/__init__.py
varsom_avalanche_client/api_client.py
varsom_avalanche_client/configuration.py
varsom_avalanche_client/rest.py
varsom_avalanche_client/api/__init__.py
varsom_avalanche_client/api/archive_api.py
varsom_avalanche_client/api/avalanche_warning_by_coordinates_api.py
varsom_avalanche_client/api/avalanche_warning_by_region_api.py
varsom_avalanche_client/api/cap_api.py
varsom_avalanche_client/api/region_api.py
varsom_avalanche_client/api/region_summary_api.py
varsom_avalanche_client/api/warning_api.py
varsom_avalanche_client/models/__init__.py
varsom_avalanche_client/models/advice.py
varsom_avalanche_client/models/alert.py
varsom_avalanche_client/models/alert_info.py
varsom_avalanche_client/models/alert_info_area.py
varsom_avalanche_client-1.0.0.dist-info/LICENSE
varsom_avalanche_client-1.0.0.dist-info/METADATA
varsom_avalanche_client-1.0.0.dist-info/WHEEL
varsom_avalanche_client-1.0.0.dist-info/top_level.txt
varsom_avalanche_client-1.0.0.dist-info/RECORD
